{
    "init": ["Movie/TV Show Recommendation Engine", "What would you like?", "Movie", "TV Show", "", ""],
    "Movie": ["", "What genre do you enjoy?", "Action", "Adventure", "Romance", "Mystery"],
    "Action": ["", "Do you want a new or old movie?", "Recent", "Old", "", ""],
    "Adventure": ["", "Do you want a survival or an exploration theme?", "Survival", "Exploration", "", ""],
    "Romance": ["", "Do you want a light-hearted or dramatic movie?", "Light-hearted", "Dramatic", "", ""],
    "Mystery": ["", "Do you want a crime or noir mystery movie?", "Crime", "Noir", "", ""],
    "Recent": ["", "Here is a recent action movie!", "Lone Survivor", "", "", ""],
    "Old": ["", "Here is an old action movie!", "The Day After Tomorrow", "", "", ""],
    "Survial": ["", "Here is a survival adventure movie!", "127 Hours", "", "", ""],
    "Exploration": ["", "Here is an exploration adventure movie!", "Intersteller", "", "", ""],
    "Light-hearted": ["", "Here is a light-hearted romance movie!", "Crazy Rich Asians", "", "", ""],
    "Dramatic": ["", "Here is a dramatic romance movie!", "The Notebook", "", "", ""],
    "Crime": ["", "Here is a crime mystery movie!", "Seven", "", "", ""],
    "Noir": ["", "Here is a noir mystery movie!", "Memento", "", "", ""],
    "TV Show": ["", "What genre do you enjoy?", "Comedy", "Sci-fi", "Fantasy", ""],
    "Comedy": ["", "Do you want a family-friendly show?", "Yes", "No", "", ""],
    "Sci-fi": ["", "Do you prefer long-running or short TV shows?", "Long", "Short", "", ""],
    "Fantasy": ["", "Do you want a modern or ancient setting?", "Modern", "Ancient", "", ""],
    "Yes": ["", "Here is a family-friendly comedy!", "Phineas and Ferb", "", "", ""],
    "No": ["", "Here is an adult comedy!", "Solar Opposites", "", "", ""],
    "Long": ["", "Here is a long-running sci-fi TV show!", "Doctor Who", "", "", ""],
    "Short": ["", "Here is a short-running sci-fi TV show!", "Firefly", "", "", ""],
    "Modern": ["", "Here is a modern setting fantasy TV show!", "Charmed", "", "", ""],
    "Ancient": ["", "Here is an ancient setting fantasy TV show!", "The Witcher", "", "", ""]
}